iflow_mcp_erniebrodeur_mcp_grep-0.2.1.dist-info/licenses/LICENSE
mcp_grep/__init__.py
mcp_grep/core.py
mcp_grep/inspector.py
mcp_grep/server.py
iflow_mcp_erniebrodeur_mcp_grep-0.2.1.dist-info/METADATA
iflow_mcp_erniebrodeur_mcp_grep-0.2.1.dist-info/WHEEL
iflow_mcp_erniebrodeur_mcp_grep-0.2.1.dist-info/entry_points.txt
iflow_mcp_erniebrodeur_mcp_grep-0.2.1.dist-info/top_level.txt
iflow_mcp_erniebrodeur_mcp_grep-0.2.1.dist-info/RECORD
